LICENSE
MANIFEST.in
README.rst
setup.cfg
setup.py
drf_django_flexible_subscriptions.egg-info/PKG-INFO
drf_django_flexible_subscriptions.egg-info/SOURCES.txt
drf_django_flexible_subscriptions.egg-info/dependency_links.txt
drf_django_flexible_subscriptions.egg-info/requires.txt
drf_django_flexible_subscriptions.egg-info/top_level.txt
subscriptions_api/__init__.py
subscriptions_api/admin.py
subscriptions_api/app_settings.py
subscriptions_api/base_models.py
subscriptions_api/models.py
subscriptions_api/notifications.py
subscriptions_api/permissions.py
subscriptions_api/serializers.py
subscriptions_api/signals.py
subscriptions_api/urls.py
subscriptions_api/views.py
subscriptions_api/migrations/0001_initial.py
subscriptions_api/migrations/0002_auto_20200512_1405.py
subscriptions_api/migrations/0003_subscriptionplan_feature_ref.py
subscriptions_api/migrations/0004_auto_20200908_1400.py
subscriptions_api/migrations/0005_auto_20201017_0651.py
subscriptions_api/migrations/0006_usersubscription_reference.py
subscriptions_api/migrations/0007_auto_20201117_1209.py
subscriptions_api/migrations/0008_auto_20210128_0337.py
subscriptions_api/migrations/0009_alter_subscriptionplan_options_and_more.py
subscriptions_api/migrations/0010_plancost_min_subscription_quantity.py
subscriptions_api/migrations/__init__.py