Metadata-Version: 2.1
Name: drf-django-flexible-subscriptions
Version: 1.0.1
Summary: Expose API views for Django Flexible Subscriptions
Home-page: https://github.com/ydaniels/drf-django-flexible-subscriptions
Author: Yomi Daniels
Author-email: yomid4all@gmail.com
License: BSD
Platform: UNKNOWN
Classifier: Development Status :: 2 - Pre-Alpha
Classifier: Environment :: Web Environment
Classifier: Framework :: Django
Classifier: Intended Audience :: Developers
Classifier: License :: OSI Approved :: BSD License
Classifier: Operating System :: OS Independent
Classifier: Natural Language :: English
Classifier: Programming Language :: Python :: 3.6
Classifier: Programming Language :: Python :: 3.7
Classifier: Programming Language :: Python :: 3.8
Classifier: Topic :: Internet :: WWW/HTTP
License-File: LICENSE
